setup.py
django_transformfiles.egg-info/PKG-INFO
django_transformfiles.egg-info/SOURCES.txt
django_transformfiles.egg-info/dependency_links.txt
django_transformfiles.egg-info/top_level.txt
transformfiles/__init__.py
transformfiles/apps.py
transformfiles/finders.py
transformfiles/manifest.py
transformfiles/storage.py
transformfiles/tests.py
transformfiles/transforms.py
transformfiles/contrib/__init__.py
transformfiles/contrib/transforms/__init__.py
transformfiles/contrib/transforms/scss.py
transformfiles/management/commands/show_registered_transforms.py